build/lib/build/lib/build/lib/build/lib/build/lib/build/lib/build/lib/build/lib/toolkit/__init__.py
build/lib/build/lib/build/lib/build/lib/build/lib/build/lib/build/lib/build/lib/toolkit/common.py
build/lib/build/lib/build/lib/build/lib/build/lib/build/lib/build/lib/build/lib/toolkit/ssm_connect.py
build/lib/build/lib/build/lib/build/lib/build/lib/build/lib/build/lib/build/lib/toolkit/ssm_list.py
build/lib/build/lib/build/lib/build/lib/build/lib/build/lib/build/lib/build/lib/toolkit/ssm_port_forward.py
build/lib/build/lib/build/lib/build/lib/build/lib/build/lib/build/lib/build/lib/toolkit/ssm_run.py
build/lib/build/lib/build/lib/build/lib/build/lib/build/lib/build/lib/build/lib/toolkit/ssm_ssh.py
build/lib/build/lib/build/lib/build/lib/build/lib/build/lib/build/lib/toolkit/__init__.py
build/lib/build/lib/build/lib/build/lib/build/lib/build/lib/build/lib/toolkit/common.py
build/lib/build/lib/build/lib/build/lib/build/lib/build/lib/build/lib/toolkit/ssm_connect.py
build/lib/build/lib/build/lib/build/lib/build/lib/build/lib/build/lib/toolkit/ssm_list.py
build/lib/build/lib/build/lib/build/lib/build/lib/build/lib/build/lib/toolkit/ssm_port_forward.py
build/lib/build/lib/build/lib/build/lib/build/lib/build/lib/build/lib/toolkit/ssm_run.py
build/lib/build/lib/build/lib/build/lib/build/lib/build/lib/build/lib/toolkit/ssm_ssh.py
build/lib/build/lib/build/lib/build/lib/build/lib/build/lib/toolkit/__init__.py
build/lib/build/lib/build/lib/build/lib/build/lib/build/lib/toolkit/common.py
build/lib/build/lib/build/lib/build/lib/build/lib/build/lib/toolkit/ssm_connect.py
build/lib/build/lib/build/lib/build/lib/build/lib/build/lib/toolkit/ssm_list.py
build/lib/build/lib/build/lib/build/lib/build/lib/build/lib/toolkit/ssm_port_forward.py
build/lib/build/lib/build/lib/build/lib/build/lib/build/lib/toolkit/ssm_run.py
build/lib/build/lib/build/lib/build/lib/build/lib/build/lib/toolkit/ssm_ssh.py
build/lib/build/lib/build/lib/build/lib/build/lib/toolkit/__init__.py
aws_systems_manager_toolkit-0.0.7.dist-info/METADATA
aws_systems_manager_toolkit-0.0.7.dist-info/WHEEL
aws_systems_manager_toolkit-0.0.7.dist-info/entry_points.txt
aws_systems_manager_toolkit-0.0.7.dist-info/top_level.txt
aws_systems_manager_toolkit-0.0.7.dist-info/RECORD
