Metadata-Version: 2.1
Name: aws-systems-manager-toolkit
Version: 0.0.7
Summary: Wrapper tools for AWS Systems Manager
Home-page: https://github.com/vonage/aws-systems-manager-toolkit
Author: Vonage SRE
Author-email: sre@vonage.com
License: MIT
Platform: UNKNOWN
Classifier: License :: OSI Approved :: MIT License
Classifier: Operating System :: POSIX :: Linux
Classifier: Operating System :: MacOS :: MacOS X
Classifier: Operating System :: Microsoft :: Windows :: Windows 10
Classifier: Programming Language :: Python :: 3 :: Only
Classifier: Programming Language :: Python :: 3.6
Classifier: Programming Language :: Python :: 3.7
Classifier: Programming Language :: Python :: 3.8
Requires-Python: >=3.6.0
Requires-Dist: boto3
Requires-Dist: botocore
